caterpillar/__init__.py
caterpillar/composition.py
caterpillar/conftest.py
caterpillar/locking.py
caterpillar/test_util.py
caterpillar/processing/__init__.py
caterpillar/processing/index.py
caterpillar/processing/plugin.py
caterpillar/processing/schema.py
caterpillar/processing/analysis/__init__.py
caterpillar/processing/analysis/analyse.py
caterpillar/processing/analysis/filter.py
caterpillar/processing/analysis/stopwords.py
caterpillar/processing/analysis/tokenize.py
caterpillar/resources/__init__.py
caterpillar/resources/stopwords-english-test.txt
caterpillar/resources/stopwords-english.txt
caterpillar/resources/stopwords-malay.txt
caterpillar/storage/__init__.py
caterpillar/storage/_sqlite_migrations.py
caterpillar/storage/_sqlite_scripts.py
caterpillar/storage/sqlite.py
caterpillar-0.15.10.dist-info/DESCRIPTION.rst
caterpillar-0.15.10.dist-info/METADATA
caterpillar-0.15.10.dist-info/RECORD
caterpillar-0.15.10.dist-info/WHEEL
caterpillar-0.15.10.dist-info/metadata.json
caterpillar-0.15.10.dist-info/top_level.txt
