Metadata-Version: 2.0
Name: caterpillar
Version: 0.15.10
Summary: Text retrieval and analytics engine.
Home-page: https://github.com/Kapiche/caterpillar
Author: Kapiche
Author-email: contact@kapiche.com
License: AGPLv3+
Keywords: indexing text analytics
Platform: UNKNOWN
Classifier: Development Status :: 3 - Alpha
Classifier: Intended Audience :: Developers
Classifier: Intended Audience :: Science/Research
Classifier: Programming Language :: Python :: 3 :: Only
Classifier: Programming Language :: Python :: 3.5
Classifier: Programming Language :: Python :: 3.6
Classifier: License :: OSI Approved :: GNU Affero General Public License v3 or later (AGPLv3+)
Classifier: Topic :: Database :: Database Engines/Servers
Classifier: Topic :: Scientific/Engineering :: Information Analysis
Classifier: Topic :: Text Processing :: Indexing
Provides-Extra: test
Requires-Dist: apsw
Requires-Dist: arrow
Requires-Dist: nltk (>=3.0)
Requires-Dist: regex
Provides-Extra: test
Requires-Dist: coverage; extra == 'test'
Requires-Dist: mock; extra == 'test'
Requires-Dist: pep8; extra == 'test'
Requires-Dist: pytest; extra == 'test'
Requires-Dist: pytest-cov; extra == 'test'
Requires-Dist: tox; extra == 'test'
